orgo/__init__.py
orgo/computer.py
orgo/forge.py
orgo/project.py
orgo/prompt.py
orgo/api/__init__.py
orgo/api/client.py
orgo/utils/__init__.py
orgo/utils/auth.py
orgo-0.0.40.dist-info/METADATA
orgo-0.0.40.dist-info/WHEEL
orgo-0.0.40.dist-info/top_level.txt
orgo-0.0.40.dist-info/RECORD
