Metadata-Version: 2.4
Name: orgo
Version: 0.0.40
Summary: Computers for AI agents
Author: Orgo Team
License: MIT
Project-URL: Homepage, https://www.orgo.ai
Project-URL: Documentation, https://docs.orgo.ai
Requires-Python: >=3.7
Requires-Dist: requests>=2.28.0
Requires-Dist: pillow>=9.0.0
Requires-Dist: anthropic>=0.50.0
Requires-Dist: websocket-client>=1.6.0
